kpmgdev/mlflow/__init__.py
kpmgdev/mlflow/logging.py
kpmgdev/mlflow/mlflow_utils_class.py
kpmgdev/mlflow/server.py
kpmgdev_mlflow-1.0.15.dist-info/LICENSE.txt
kpmgdev_mlflow-1.0.15.dist-info/METADATA
kpmgdev_mlflow-1.0.15.dist-info/WHEEL
kpmgdev_mlflow-1.0.15.dist-info/top_level.txt
kpmgdev_mlflow-1.0.15.dist-info/RECORD
